wordfencer
