Metadata-Version: 1.1
Name: wordfencer
Version: 1.2.9
Summary: Parser for natural languages without space delimiters
Home-page: https://github.com/bobbyesh/word-fencer
Author: Bobby Eshleman
Author-email: bobbyeshleman@gmail.com
License: UNKNOWN
Platform: UNKNOWN
Classifier: Programming Language :: Python
Classifier: Programming Language :: Python :: 3
Classifier: License :: OSI Approved :: MIT License
Classifier: Programming Language :: Python :: 3
Classifier: Natural Language :: Cantonese
Classifier: Natural Language :: Chinese (Simplified)
Classifier: Natural Language :: Chinese (Traditional)
Classifier: Natural Language :: Thai
